admin_tool_button/__init__.py
admin_tool_button/version.py
admin_tool_button/contrib/__init__.py
admin_tool_button/contrib/admin.py
admin_tool_button-1.0.7a0.dist-info/METADATA
admin_tool_button-1.0.7a0.dist-info/WHEEL
admin_tool_button-1.0.7a0.dist-info/top_level.txt
admin_tool_button-1.0.7a0.dist-info/RECORD
