Metadata-Version: 2.1
Name: admin_tool_button
Version: 1.0.7a0
Summary: Extra tool buttons for Django admin
Home-page: https://github.com/bboogaard/admin_tool_button
Author: Bram Boogaard
Author-email: padawan@hetnet.nl
License: MIT License
Keywords: Django Admin
Classifier: Development Status :: 3 - Alpha
Requires-Dist: pytest
Requires-Dist: pytest-cov
Requires-Dist: pytest-django ==4.5.2
Requires-Dist: django ~=4.2.9
